who_cares/__init__.py
who_cares/__main__.py
who_cares-0.1.0.dist-info/METADATA
who_cares-0.1.0.dist-info/WHEEL
who_cares-0.1.0.dist-info/entry_points.txt
who_cares-0.1.0.dist-info/RECORD
