Metadata-Version: 2.3
Name: who-cares
Version: 0.1.0
Summary: Who cares, I'm already late.
Author: Stefano Palazzo
Author-email: stefano.palazzo@gmail.com
Requires-Python: >=3.13,<4
Classifier: Programming Language :: Python :: 3
Classifier: Programming Language :: Python :: 3.13
Requires-Dist: docopt-ng (>=0.9.0,<0.10.0)
